{
  "project_info": {
    "project_number": "981948807681",
    "project_id": "firstapp-75c10",
    "storage_bucket": "firstapp-75c10.appspot.com"
  },
  "client": [
    {
      "client_info": {
        "mobilesdk_app_id": "1:981948807681:android:41b029a4ab30902e009e00",
        "android_client_info": {
          "package_name": "com.example.firstapplication"
        }
      },
      "oauth_client": [],
      "api_key": [
        {
          "current_key": "AIzaSyDjEd4qD_1HoR4yXvhcvRgc0KfPrJ7uWAY"
        }
      ],
      "services": {
        "appinvite_service": {
          "other_platform_oauth_client": []
        }
      }
    }
  ],
  "configuration_version": "1"
}